shiftRegIn.v
// *****************************************************************************
// *                     C O P Y R I G H T   N O T I C E                       *
// *****************************************************************************
// *                                                                           *
// * Confidential                                                              *
// *                                                                           *
// * (c) Copyright 2011-2016 Hewlett Packard Enterprise Development LP         *
// *                                                                           *
// * Copyrights. You may not duplicate, install or use software in violation   *
// * of its copyright or applicable license terms, including the software      *
// * installed on your computer or on network areas under your control. Unless *
// * proper permission has been obtained from the copyright owner, you may not *
// * copy for any reason any copyrighted materials, including text, artwork,   *
// * images, photographs, videos, music, web pages and other forms of          *
// * expression, whether they are in hardcopy or electronic media.             *
// *                                                                           *
// *****************************************************************************
// * HPE Engineer: Jonathan Pham                                               *
// * Design Name : Adaptive NVMe code                                          *
// * Description : Serial to Parallel input data to Adaptive NVMe Card's CPLD  *
// *****************************************************************************

module shiftRegIn #(
	parameter TOTAL_BIT_COUNT = 8)(

    // Input Clocks and Resets
    input 						 serclk, 
    input 						 reset_n,

    // SERIAL Data In from baseboard
    input                        ser_data_in,

    // Shift Control Bits
    input 						 ser_load_in_n,

    // PARALLEL Output
    output reg [TOTAL_BIT_COUNT-1:0] p_out
   );
 	

 	reg [TOTAL_BIT_COUNT-1:0]   shift_reg;

 	//------------------------------------------------------------------------------
	// Parallel to Serial Converter
    // When in reset: shift register contains all 0s
    // When out of reset:
    //          When load_n is enabled:  Grab serial data in 1 by 1 into shift register
    //          When load_n not enabled: push out all bits in shift register simultaneously
	//------------------------------------------------------------------------------
   
    always@(posedge serclk or negedge reset_n)begin
    	if (!reset_n)begin
            p_out     <= {TOTAL_BIT_COUNT{1'b0}}; 
    		shift_reg <= {TOTAL_BIT_COUNT{1'b0}};
             
    	end
    	else begin
    		if (!ser_load_in_n)begin
    			shift_reg = {ser_data_in,shift_reg[TOTAL_BIT_COUNT-1:1]};
    		end
    		else begin
    			p_out = shift_reg;
    		end
    	end
    end
    

endmodule

shiftRegIn_tb.v
`timescale 1ns / 10ps
module shiftRegInTB;
	parameter Total = 8;
	// Inputs
	reg serclk = 0;
	reg reset_n;
	reg ser_load_in_n;
	reg sdi;

	// Outputs
	wire [7:0] p_out;

	// Instantiate the Unit Under Test (UUT)
	shiftRegIn  #(8) s1  (
		.serclk(serclk), 
		.reset_n(reset_n), 
		.ser_load_in_n(ser_load_in_n),
		.ser_data_in(sdi),
		.p_out(p_out[7:0])

	);
 

 
always	  	#1 serclk = ~serclk;
	 
  
 
initial begin
 
$dumpfile("pvt_gpi.vcd");
$dumpvars(0,s1);
 
reset_n = 0;
ser_load_in_n = 0;
sdi = {8{1'b0}};
#5 reset_n = 1;
#5 sdi = 1;
#5 ser_load_in_n = 0;
#5 ser_load_in_n = 1;
#5 ser_load_in_n = 0;
#5 reset_n = 0;
#2 $finish;

 end  
 
		initial begin
		 $monitor("serclk=%d sdi=%d,p_out=%d, ser_load_in_n=%d",serclk, sdi, p_out, ser_load_in_n);
		 end
 
endmodule

pvt_gpi.vcd
$date
	Sat Sep 15 19:35:00 2018
$end
$version
	Icarus Verilog
$end
$timescale
	10ps
$end
$scope module shiftRegInTB $end
$scope module s1 $end
$var wire 1 ! reset_n $end
$var wire 1 " ser_data_in $end
$var wire 1 # ser_load_in_n $end
$var wire 1 $ serclk $end
$var reg 8 % p_out [7:0] $end
$var reg 8 & shift_reg [7:0] $end
$upscope $end
$upscope $end
$enddefinitions $end
#0
$dumpvars
b0 &
b0 %
0$
0#
0"
0!
$end
#100
1$
#200
0$
#300
1$
#400
0$
#500
1$
1!
#600
0$
#700
1$
#800
0$
#900
1$
#1000
0$
1"
#1100
b10000000 &
1$
#1200
0$
#1300
b11000000 &
1$
#1400
0$
#1500
b11100000 &
1$
#1600
0$
#1700
b11110000 &
1$
#1800
0$
#1900
b11111000 &
1$
#2000
0$
1#
#2100
b11111000 %
1$
#2200
0$
#2300
1$
#2400
0$
#2500
b11111100 &
1$
0#
#2600
0$
#2700
b11111110 &
1$
#2800
0$
#2900
b11111111 &
1$
#3000
b0 &
b0 %
0$
0!
