shiftReg.v
// *****************************************************************************
// *                     C O P Y R I G H T   N O T I C E                       *
// *****************************************************************************
// *                                                                           *
// * Confidential                                                              *
// *                                                                           *
// * (c) Copyright 2011-2016 Hewlett Packard Enterprise Development LP         *
// *                                                                           *
// * Copyrights. You may not duplicate, install or use software in violation   *
// * of its copyright or applicable license terms, including the software      *
// * installed on your computer or on network areas under your control. Unless *
// * proper permission has been obtained from the copyright owner, you may not *
// * copy for any reason any copyrighted materials, including text, artwork,   *
// * images, photographs, videos, music, web pages and other forms of          *
// * expression, whether they are in hardcopy or electronic media.             *
// *                                                                           *
// *****************************************************************************
// * HPE Engineer: Jonathan Pham                                               *
// * Design Name : Adaptive NVMe code                                          *
// * Description : Parallel to Serial Data Output to System CPLD               *
// *****************************************************************************

module shiftReg #(
	parameter TOTAL_BIT_COUNT = 8)(

    // Input Clocks and Resets
    input 						serclk, 
    input 						reset_n,

    // Parallel Data In
    input [TOTAL_BIT_COUNT-1:0] par_data_in,

    // Shift Control Bits
    input 						par_load_in_n,

    // Serial Output
    output 						s_out
   );
 	

 	reg [TOTAL_BIT_COUNT-1:0]   shift_reg;

 	//------------------------------------------------------------------------------
	// Parallel to Serial Converter
	//------------------------------------------------------------------------------
   
    always@(posedge serclk or negedge reset_n)begin
    	if (!reset_n)begin
    		shift_reg = {TOTAL_BIT_COUNT{1'b0}};
    	end
    	else begin
    		if (!par_load_in_n)begin
    			shift_reg = par_data_in;
    		end
    		else begin
    			shift_reg = {1'b0,shift_reg[TOTAL_BIT_COUNT-1:1]};
    		end
    	end
    end
 	
 	assign s_out = shift_reg[0];
 
endmodule

shiftReg_tb.v
`timescale 1ns / 10ps
module shiftRegTB;
	parameter Total = 8;
	// Inputs
	reg serclk = 0;
	reg reset_n;
	reg par_load_in_n;
	reg [7:0] par_data_in;

	// Outputs
	wire s_out;

	// Instantiate the Unit Under Test (UUT)
	shiftReg  #(8) s1  (
		.serclk(serclk), 
		.reset_n(reset_n), 
		.par_load_in_n(par_load_in_n),
		.par_data_in(par_data_in[7:0]),
		.s_out(s_out)

	);
 

 
always	  	#1 serclk = ~serclk;
	 
 
 
initial begin
 
$dumpfile("test.vcd");
$dumpvars(0,s1);
 
reset_n = 0;
par_load_in_n = 0;
par_data_in = {8{1'b0}};
#5 reset_n = 1;
#5 par_data_in = {8{1'b1}};
#5 par_load_in_n = 0;
#5 par_load_in_n = 1;
#5 par_load_in_n = 0;
#1 par_load_in_n = 1;
#5 reset_n = 0;
#2 $finish;

 end  
 
		initial begin
		 $monitor("serclk=%d par_data_in=%d,s_out=%d, par_load_in_n=%d",serclk, par_data_in, s_out, par_load_in_n);
		 end
 
endmodule

test.vcd
$date
	Sat Jul 07 14:57:20 2018
$end
$version
	Icarus Verilog
$end
$timescale
	10ps
$end
$scope module shiftRegTB $end
$scope module s1 $end
$var wire 8 ! par_data_in [7:0] $end
$var wire 1 " par_load_in_n $end
$var wire 1 # reset_n $end
$var wire 1 $ serclk $end
$var wire 1 % s_out $end
$var reg 8 & shift_reg [7:0] $end
$upscope $end
$upscope $end
$enddefinitions $end
#0
$dumpvars
b0 &
0%
0$
0#
0"
b0 !
$end
#100
1$
#200
0$
#300
1$
#400
0$
#500
1$
1#
#600
0$
#700
1$
#800
0$
#900
1$
#1000
0$
b11111111 !
#1100
1%
b11111111 &
1$
#1200
0$
#1300
1$
#1400
0$
#1500
1$
#1600
0$
#1700
1$
#1800
0$
#1900
1$
#2000
0$
1"
#2100
b1111111 &
1$
#2200
0$
#2300
b111111 &
1$
#2400
0$
#2500
b11111111 &
1$
0"
#2600
0$
1"
#2700
b1111111 &
1$
#2800
0$
#2900
b111111 &
1$
#3000
0$
#3100
0%
b0 &
1$
0#
